CHANGELOG.md
LICENSE
MANIFEST.in
README.md
package.json
setup.py
dash_glue42/Channels.py
dash_glue42/Context.py
dash_glue42/Contexts.py
dash_glue42/Glue42.py
dash_glue42/MethodInvoke.py
dash_glue42/MethodRegister.py
dash_glue42/Notifications.py
dash_glue42/Windows.py
dash_glue42/__init__.py
dash_glue42/_imports_.py
dash_glue42/dash_glue42.min.js
dash_glue42/dash_glue42.min.js.map
dash_glue42/metadata.json
dash_glue42/package-info.json
dash_glue42.egg-info/PKG-INFO
dash_glue42.egg-info/SOURCES.txt
dash_glue42.egg-info/dependency_links.txt
dash_glue42.egg-info/top_level.txt
tests/test_usage.py