Metadata-Version: 2.1
Name: dash-glue42
Version: 1.4.0a0
Summary: Dash components for Glue42
Author: Glue42
License: MIT
Project-URL: Home, https://glue42.com/
Project-URL: Documentation, https://docs.glue42.com/getting-started/how-to/glue42-enable-your-app/dash/index.html
Classifier: Framework :: Dash
Requires-Python: >=3.6
License-File: LICENSE
